provablyfair/__init__.py
provablyfair/py.typed
provablyfair-1.0.0.dist-info/LICENSE
provablyfair-1.0.0.dist-info/METADATA
provablyfair-1.0.0.dist-info/WHEEL
provablyfair-1.0.0.dist-info/top_level.txt
provablyfair-1.0.0.dist-info/RECORD
