Metadata-Version: 2.1
Name: provablyfair
Version: 1.0.0
Summary: Provably fair for Python
Home-page: https://github.com/SaidBySolo/provablyfair
Author: Ryu ju heon
Author-email: saidbysolo@gmail.com
License: MIT
Platform: any
Classifier: License :: OSI Approved :: MIT License
Classifier: Operating System :: OS Independent
Requires-Python: >=3.6
License-File: LICENSE
